simphony_osp/__init__.py
simphony_osp/development.py
simphony_osp/namespaces.py
simphony_osp/wrappers.py
simphony_osp/interfaces/__init__.py
simphony_osp/interfaces/interface.py
simphony_osp/interfaces/dataspace/__init__.py
simphony_osp/interfaces/dataspace/interface.py
simphony_osp/interfaces/remote/__init__.py
simphony_osp/interfaces/remote/client.py
simphony_osp/interfaces/remote/common.py
simphony_osp/interfaces/remote/engine.py
simphony_osp/interfaces/remote/server.py
simphony_osp/interfaces/sqlalchemy/__init__.py
simphony_osp/interfaces/sqlalchemy/interface.py
simphony_osp/interfaces/sqlite/__init__.py
simphony_osp/interfaces/sqlite/interface.py
simphony_osp/ontology/__init__.py
simphony_osp/ontology/annotation.py
simphony_osp/ontology/attribute.py
simphony_osp/ontology/composition.py
simphony_osp/ontology/entity.py
simphony_osp/ontology/individual.py
simphony_osp/ontology/namespace.py
simphony_osp/ontology/oclass.py
simphony_osp/ontology/relationship.py
simphony_osp/ontology/restriction.py
simphony_osp/ontology/utils.py
simphony_osp/ontology/files/__init__.py
simphony_osp/ontology/files/city.ttl
simphony_osp/ontology/files/city.yml
simphony_osp/ontology/files/dcam.yml
simphony_osp/ontology/files/dcat.yml
simphony_osp/ontology/files/dcelements.yml
simphony_osp/ontology/files/dcmitype.yml
simphony_osp/ontology/files/dcterms.yml
simphony_osp/ontology/files/emmo-datamodel.yml
simphony_osp/ontology/files/emmo.yml
simphony_osp/ontology/files/foaf.yml
simphony_osp/ontology/files/owl.ttl
simphony_osp/ontology/files/owl.yml
simphony_osp/ontology/files/prov.yml
simphony_osp/ontology/files/rdfs.ttl
simphony_osp/ontology/files/rdfs.yml
simphony_osp/ontology/files/simphony.ttl
simphony_osp/ontology/files/simphony.yml
simphony_osp/ontology/files/skos.yml
simphony_osp/ontology/operations/__init__.py
simphony_osp/ontology/operations/container.py
simphony_osp/ontology/operations/file.py
simphony_osp/ontology/operations/operations.py
simphony_osp/ontology/parser/__init__.py
simphony_osp-4.0.0.dist-info/LICENSE.md
simphony_osp-4.0.0.dist-info/METADATA
simphony_osp-4.0.0.dist-info/WHEEL
simphony_osp-4.0.0.dist-info/entry_points.txt
simphony_osp-4.0.0.dist-info/top_level.txt
simphony_osp-4.0.0.dist-info/RECORD
