Metadata-Version: 2.1
Name: simphony-osp
Version: 4.0.0
Summary: Framework for creating interfaces between ontologies and software such as simulation engines, databases and data repositories.
Home-page: https://github.com/simphony/simphony-osp/tree/v4.0.0
Download-URL: https://pypi.org/project/simphony-osp/4.0.0/
Author: SimPhoNy, EU FP7 Project (Nr. 604005)
Maintainer: Fraunhofer IWM
Maintainer-email: simphony@iwm.fraunhofer.de
License: BSD-3-Clause
Project-URL: Tracker, https://github.com/simphony/simphony-osp/issues
Project-URL: Documentation, https://simphony.readthedocs.io/en/v4.0.0/
Project-URL: Source, https://github.com/simphony/simphony-osp/tree/v4.0.0
Keywords: owl,ontology,interoperability,materials-science,osp,simphony,wrappers,open-simulation-platform,knowledge-graphFraunhofer IWM
Classifier: Development Status :: 5 - Production/Stable
Classifier: Intended Audience :: Developers
Classifier: Intended Audience :: Science/Research
Classifier: Topic :: Scientific/Engineering
Classifier: Topic :: Software Development :: Libraries
Classifier: License :: OSI Approved :: BSD License
Classifier: Programming Language :: Python
Classifier: Programming Language :: Python :: 3 :: Only
Classifier: Programming Language :: Python :: 3.6
Classifier: Programming Language :: Python :: 3.7
Classifier: Programming Language :: Python :: 3.8
Classifier: Programming Language :: Python :: 3.9
Classifier: Programming Language :: Python :: 3.10
Classifier: Operating System :: Microsoft :: Windows
Classifier: Operating System :: MacOS
Classifier: Operating System :: Unix
Requires-Python: >=3.7
License-File: LICENSE.md
Requires-Dist: graphviz
Requires-Dist: numpy
Requires-Dist: PyYaml
Requires-Dist: rdflib (<7.0.0,>=6.0.2)
Requires-Dist: rdflib-sqlalchemy (>=0.5.0)
Requires-Dist: requests
Requires-Dist: websockets (<11,>=9)
Requires-Dist: importlib-metadata (<6,>=5) ; python_version <= "3.7"
Requires-Dist: websockets (>=10) ; python_version >= "3.10"
